{
  "ClassName": "Mage",
  "Loot": true,
  "NPCMaxLevels_Below": 6,

  "PathFilename": "D:\\GitHub\\WowPixelBot\\26_Wetlands.json",
  "SpiritPathFilename": "D:\\GitHub\\WowPixelBot\\26_Wetlands_SpiritHealer.json",
  "PathThereAndBack": true,
  "PathReduceSteps": true,
  
  //"WrongZone": { "ZoneId": 1429, "ExitZoneLocation": { "X":62.5,"Y":90} },

  "Blacklist": ["Tunnel","OL' SO","HAREN S","THRAGO"],

  "Pull": {
    "Sequence": [
      {
        "Name": "Pyroblast",
        "HasCastBar": true,
        "Key": "-",
        "MinMana": 125,
        "DelayAfterCast" : 500
      }
    ]
  },
  "Combat": {
    "Sequence": [
      {
        "Name": "Frost Bolt",
        "HasCastBar": true,
        "Key": "5",
        "MinMana": 50,
        "Cooldown": 6
      },
      {
        "Name": "Fire Blast",
        "Key": "1",
        "MinMana": 75,
        "Cooldown": 8
      },
      {
        "Name": "Fireball",
        "HasCastBar": true,
        "Key": "2",
        "MinMana": 45,
        "DelayAfterCast" : 500
      }
    ]
  },
  "Adhoc": {
    "Sequence": [
      {
        "Name": "Frost Armor",
        "StopBeforeCast": false,
        "Key": "3",
        "MinMana": 110,
        "Requirement": "not Frost Armor",
        "Log": false
      },
      {
        "Name": "Arcane Intellect",
        "StopBeforeCast": false,
        "Key": "4",
        "MinMana": 60,
        "Requirement": "not Arcane Intellect",
        "Log": false
      },
      {
        "Name": "Low Health",
        "HasCastBar": true,
        "StopBeforeCast": true,
        "Key": "6",
        "Requirement": "Health%<70",
        "Log": false,
        "Cost": 3
      },
      {
        "Name": "Drink",
        "HasCastBar": true,
        "StopBeforeCast": true,
        "Key": "8",
        "Requirement": "Mana%<70",
        "Cooldown": 10,
        "Log": false,
        "Cost": 3
      },
      {
        "Name": "Conjure Water",
        "HasCastBar": true,
        "StopBeforeCast": true,
        "Key": "9",
        "Requirement": "not BagItem:2288",
        "Cooldown": 300,
        "Log": false
      },
      {
        "Name": "Conjure Food",
        "HasCastBar": true,
        "StopBeforeCast": true,
        "Key": "7",
        "Requirement": "not BagItem:1113",
        "Cooldown": 300,
        "Log": false
      },
      {
        "Name": "Well Fed",
        "StopBeforeCast": true,
        "Key": "=",
        "Requirement": "not Well Fed",
        "Cooldown": 120,
        "Log": false
      }
    ]
  }
}
