[
  {
    "ID": 4,
    "MapID": 1,
    "AreaID": 14,
    "AreaName": "Durotar",
    "LocLeft": -1962.4999,
    "LocRight": -7249.9995,
    "LocTop": 1808.3333,
    "LocBottom": -1716.6666,
    "UIMapId": 1411,
    "Continent": "Kalimdor"
  },
  {
    "ID": 9,
    "MapID": 1,
    "AreaID": 215,
    "AreaName": "Mulgore",
    "LocLeft": 2047.9166,
    "LocRight": -3089.5833,
    "LocTop": -272.91666,
    "LocBottom": -3697.9165,
    "UIMapId": 1412,
    "Continent": "Kalimdor"
  },
  {
    "ID": 11,
    "MapID": 1,
    "AreaID": 17,
    "AreaName": "TheBarrens",
    "LocLeft": 2622.9165,
    "LocRight": -7510.4165,
    "LocTop": 1612.4999,
    "LocBottom": -5143.75,
    "UIMapId": 1413,
    "Continent": "Kalimdor"
  },
  {
    "ID": 13,
    "MapID": 1,
    "AreaID": 0,
    "AreaName": "Kalimdor",
    "LocLeft": 17066.6,
    "LocRight": -19733.21,
    "LocTop": 12799.9,
    "LocBottom": -11733.3,
    "UIMapId": 1464,
    "Continent": "Azeroth"
  },
  {
    "ID": 14,
    "MapID": 0,
    "AreaID": 0,
    "AreaName": "Azeroth",
    "LocLeft": 16000.0,
    "LocRight": -19199.9,
    "LocTop": 7466.6,
    "LocBottom": -16000.0,
    "UIMapId": 947,
    "Continent": "Azeroth"
  },
  {
    "ID": 15,
    "MapID": 0,
    "AreaID": 36,
    "AreaName": "Alterac",
    "LocLeft": 783.3333,
    "LocRight": -2016.6666,
    "LocTop": 1500.0,
    "LocBottom": -366.66666,
    "UIMapId": 1416,
    "Continent": "Azeroth"
  },
  {
    "ID": 16,
    "MapID": 0,
    "AreaID": 45,
    "AreaName": "Arathi",
    "LocLeft": -866.6666,
    "LocRight": -4466.6665,
    "LocTop": -133.33333,
    "LocBottom": -2533.3333,
    "UIMapId": 1417,
    "Continent": "Azeroth"
  },
  {
    "ID": 17,
    "MapID": 0,
    "AreaID": 3,
    "AreaName": "Badlands",
    "LocLeft": -2079.1665,
    "LocRight": -4566.6665,
    "LocTop": -5889.583,
    "LocBottom": -7547.9165,
    "UIMapId": 1418,
    "Continent": "Azeroth"
  },
  {
    "ID": 19,
    "MapID": 0,
    "AreaID": 4,
    "AreaName": "BlastedLands",
    "LocLeft": -1241.6666,
    "LocRight": -4591.6665,
    "LocTop": -10566.666,
    "LocBottom": -12800.0,
    "UIMapId": 1419,
    "Continent": "Azeroth"
  },
  {
    "ID": 20,
    "MapID": 0,
    "AreaID": 85,
    "AreaName": "Tirisfal",
    "LocLeft": 3033.3333,
    "LocRight": -1485.4166,
    "LocTop": 3837.4998,
    "LocBottom": 824.99994,
    "UIMapId": 1420,
    "Continent": "Azeroth"
  },
  {
    "ID": 21,
    "MapID": 0,
    "AreaID": 130,
    "AreaName": "Silverpine",
    "LocLeft": 3449.9998,
    "LocRight": -750.0,
    "LocTop": 1666.6666,
    "LocBottom": -1133.3333,
    "UIMapId": 1421,
    "Continent": "Azeroth"
  },
  {
    "ID": 22,
    "MapID": 0,
    "AreaID": 28,
    "AreaName": "WesternPlaguelands",
    "LocLeft": 416.66666,
    "LocRight": -3883.3333,
    "LocTop": 3366.6665,
    "LocBottom": 499.99997,
    "UIMapId": 1422,
    "Continent": "Azeroth"
  },
  {
    "ID": 23,
    "MapID": 0,
    "AreaID": 139,
    "AreaName": "EasternPlaguelands",
    "LocLeft": -2185.4165,
    "LocRight": -6056.25,
    "LocTop": 3799.9998,
    "LocBottom": 1218.75,
    "UIMapId": 1423,
    "Continent": "Azeroth"
  },
  {
    "ID": 24,
    "MapID": 0,
    "AreaID": 267,
    "AreaName": "Hillsbrad",
    "LocLeft": 1066.6666,
    "LocRight": -2133.3333,
    "LocTop": 400.0,
    "LocBottom": -1733.3333,
    "UIMapId": 1424,
    "Continent": "Azeroth"
  },
  {
    "ID": 26,
    "MapID": 0,
    "AreaID": 47,
    "AreaName": "TheHinterlands",
    "LocLeft": -1575.0,
    "LocRight": -5425.0,
    "LocTop": 1466.6666,
    "LocBottom": -1100.0,
    "UIMapId": 1425,
    "Continent": "Azeroth"
  },
  {
    "ID": 27,
    "MapID": 0,
    "AreaID": 1,
    "AreaName": "DunMorogh",
    "LocLeft": 1802.0833,
    "LocRight": -3122.9165,
    "LocTop": -3877.0833,
    "LocBottom": -7160.4165,
    "UIMapId": 1426,
    "Continent": "Azeroth"
  },
  {
    "ID": 28,
    "MapID": 0,
    "AreaID": 51,
    "AreaName": "SearingGorge",
    "LocLeft": -322.91666,
    "LocRight": -2554.1665,
    "LocTop": -6100.0,
    "LocBottom": -7587.4995,
    "UIMapId": 1427,
    "Continent": "Azeroth"
  },
  {
    "ID": 29,
    "MapID": 0,
    "AreaID": 46,
    "AreaName": "BurningSteppes",
    "LocLeft": -266.66666,
    "LocRight": -3195.8333,
    "LocTop": -7031.2495,
    "LocBottom": -8983.333,
    "UIMapId": 1428,
    "Continent": "Azeroth"
  },
  {
    "ID": 30,
    "MapID": 0,
    "AreaID": 12,
    "AreaName": "Elwynn",
    "LocLeft": 1535.4166,
    "LocRight": -1935.4166,
    "LocTop": -7939.583,
    "LocBottom": -10254.166,
    "UIMapId": 1429,
    "Continent": "Azeroth"
  },
  {
    "ID": 32,
    "MapID": 0,
    "AreaID": 41,
    "AreaName": "DeadwindPass",
    "LocLeft": -833.3333,
    "LocRight": -3333.3333,
    "LocTop": -9866.666,
    "LocBottom": -11533.333,
    "UIMapId": 1430,
    "Continent": "Azeroth"
  },
  {
    "ID": 34,
    "MapID": 0,
    "AreaID": 10,
    "AreaName": "Duskwood",
    "LocLeft": 833.3333,
    "LocRight": -1866.6666,
    "LocTop": -9716.666,
    "LocBottom": -11516.666,
    "UIMapId": 1431,
    "Continent": "Azeroth"
  },
  {
    "ID": 35,
    "MapID": 0,
    "AreaID": 38,
    "AreaName": "LochModan",
    "LocLeft": -1993.7499,
    "LocRight": -4752.083,
    "LocTop": -4487.5,
    "LocBottom": -6327.083,
    "UIMapId": 1432,
    "Continent": "Azeroth"
  },
  {
    "ID": 36,
    "MapID": 0,
    "AreaID": 44,
    "AreaName": "Redridge",
    "LocLeft": -1570.8333,
    "LocRight": -3741.6665,
    "LocTop": -8575.0,
    "LocBottom": -10022.916,
    "UIMapId": 1433,
    "Continent": "Azeroth"
  },
  {
    "ID": 37,
    "MapID": 0,
    "AreaID": 33,
    "AreaName": "Stranglethorn",
    "LocLeft": 2220.8333,
    "LocRight": -4160.4165,
    "LocTop": -11168.75,
    "LocBottom": -15422.916,
    "UIMapId": 1434,
    "Continent": "Azeroth"
  },
  {
    "ID": 38,
    "MapID": 0,
    "AreaID": 8,
    "AreaName": "SwampOfSorrows",
    "LocLeft": -2222.9165,
    "LocRight": -4516.6665,
    "LocTop": -9620.833,
    "LocBottom": -11150.0,
    "UIMapId": 1435,
    "Continent": "Azeroth"
  },
  {
    "ID": 39,
    "MapID": 0,
    "AreaID": 40,
    "AreaName": "Westfall",
    "LocLeft": 3016.6665,
    "LocRight": -483.3333,
    "LocTop": -9400.0,
    "LocBottom": -11733.333,
    "UIMapId": 1436,
    "Continent": "Azeroth"
  },
  {
    "ID": 40,
    "MapID": 0,
    "AreaID": 11,
    "AreaName": "Wetlands",
    "LocLeft": -389.5833,
    "LocRight": -4525.0,
    "LocTop": -2147.9165,
    "LocBottom": -4904.1665,
    "UIMapId": 1437,
    "Continent": "Azeroth"
  },
  {
    "ID": 41,
    "MapID": 1,
    "AreaID": 141,
    "AreaName": "Teldrassil",
    "LocLeft": 3814.5833,
    "LocRight": -1277.0833,
    "LocTop": 11831.25,
    "LocBottom": 8437.5,
    "UIMapId": 1438,
    "Continent": "Kalimdor"
  },
  {
    "ID": 42,
    "MapID": 1,
    "AreaID": 148,
    "AreaName": "Darkshore",
    "LocLeft": 2941.6665,
    "LocRight": -3608.3333,
    "LocTop": 8333.333,
    "LocBottom": 3966.6665,
    "UIMapId": 1439,
    "Continent": "Kalimdor"
  },
  {
    "ID": 43,
    "MapID": 1,
    "AreaID": 331,
    "AreaName": "Ashenvale",
    "LocLeft": 1699.9999,
    "LocRight": -4066.6665,
    "LocTop": 4672.9165,
    "LocBottom": 829.1666,
    "UIMapId": 1440,
    "Continent": "Kalimdor"
  },
  {
    "ID": 61,
    "MapID": 1,
    "AreaID": 400,
    "AreaName": "ThousandNeedles",
    "LocLeft": -433.3333,
    "LocRight": -4833.333,
    "LocTop": -3966.6665,
    "LocBottom": -6899.9995,
    "UIMapId": 1441,
    "Continent": "Kalimdor"
  },
  {
    "ID": 81,
    "MapID": 1,
    "AreaID": 406,
    "AreaName": "StonetalonMountains",
    "LocLeft": 3245.8333,
    "LocRight": -1637.4999,
    "LocTop": 2916.6665,
    "LocBottom": -339.5833,
    "UIMapId": 1442,
    "Continent": "Kalimdor"
  },
  {
    "ID": 101,
    "MapID": 1,
    "AreaID": 405,
    "AreaName": "Desolace",
    "LocLeft": 4233.333,
    "LocRight": -262.5,
    "LocTop": 452.0833,
    "LocBottom": -2545.8333,
    "UIMapId": 1443,
    "Continent": "Kalimdor"
  },
  {
    "ID": 121,
    "MapID": 1,
    "AreaID": 357,
    "AreaName": "Feralas",
    "LocLeft": 5441.6665,
    "LocRight": -1508.3333,
    "LocTop": -2366.6665,
    "LocBottom": -6999.9995,
    "UIMapId": 1444,
    "Continent": "Kalimdor"
  },
  {
    "ID": 141,
    "MapID": 1,
    "AreaID": 15,
    "AreaName": "Dustwallow",
    "LocLeft": -974.99994,
    "LocRight": -6225.0,
    "LocTop": -2033.3333,
    "LocBottom": -5533.333,
    "UIMapId": 1445,
    "Continent": "Kalimdor"
  },
  {
    "ID": 161,
    "MapID": 1,
    "AreaID": 440,
    "AreaName": "Tanaris",
    "LocLeft": -218.74998,
    "LocRight": -7118.7495,
    "LocTop": -5875.0,
    "LocBottom": -10475.0,
    "UIMapId": 1446,
    "Continent": "Kalimdor"
  },
  {
    "ID": 181,
    "MapID": 1,
    "AreaID": 16,
    "AreaName": "Azshara",
    "LocLeft": -3277.0833,
    "LocRight": -8347.916,
    "LocTop": 5341.6665,
    "LocBottom": 1960.4166,
    "UIMapId": 1447,
    "Continent": "Kalimdor"
  },
  {
    "ID": 182,
    "MapID": 1,
    "AreaID": 361,
    "AreaName": "Felwood",
    "LocLeft": 1641.6666,
    "LocRight": -4108.333,
    "LocTop": 7133.333,
    "LocBottom": 3299.9998,
    "UIMapId": 1448,
    "Continent": "Kalimdor"
  },
  {
    "ID": 201,
    "MapID": 1,
    "AreaID": 490,
    "AreaName": "UngoroCrater",
    "LocLeft": 533.3333,
    "LocRight": -3166.6665,
    "LocTop": -5966.6665,
    "LocBottom": -8433.333,
    "UIMapId": 1449,
    "Continent": "Kalimdor"
  },
  {
    "ID": 241,
    "MapID": 1,
    "AreaID": 493,
    "AreaName": "Moonglade",
    "LocLeft": -1381.25,
    "LocRight": -3689.5833,
    "LocTop": 8491.666,
    "LocBottom": 6952.083,
    "UIMapId": 1450,
    "Continent": "Kalimdor"
  },
  {
    "ID": 261,
    "MapID": 1,
    "AreaID": 1377,
    "AreaName": "Silithus",
    "LocLeft": 2537.5,
    "LocRight": -945.834,
    "LocTop": -5958.334,
    "LocBottom": -8281.25,
    "UIMapId": 1451,
    "Continent": "Kalimdor"
  },
  {
    "ID": 281,
    "MapID": 1,
    "AreaID": 618,
    "AreaName": "Winterspring",
    "LocLeft": -316.66666,
    "LocRight": -7416.6665,
    "LocTop": 8533.333,
    "LocBottom": 3799.9998,
    "UIMapId": 1452,
    "Continent": "Kalimdor"
  },
  {
    "ID": 301,
    "MapID": 0,
    "AreaID": 1519,
    "AreaName": "Stormwind",
    "LocLeft": 1380.9714,
    "LocRight": 36.70063,
    "LocTop": -8278.851,
    "LocBottom": -9175.205,
    "UIMapId": 1453,
    "Continent": "Azeroth"
  },
  {
    "ID": 321,
    "MapID": 1,
    "AreaID": 1637,
    "AreaName": "Orgrimmar",
    "LocLeft": -3680.601,
    "LocRight": -5083.2056,
    "LocTop": 2273.8772,
    "LocBottom": 1338.4606,
    "UIMapId": 1454,
    "Continent": "Kalimdor"
  },
  {
    "ID": 341,
    "MapID": 0,
    "AreaID": 1537,
    "AreaName": "Ironforge",
    "LocLeft": -713.5914,
    "LocRight": -1504.2164,
    "LocTop": -4569.241,
    "LocBottom": -5096.8457,
    "UIMapId": 1455,
    "Continent": "Azeroth"
  },
  {
    "ID": 362,
    "MapID": 1,
    "AreaID": 1638,
    "AreaName": "ThunderBluff",
    "LocLeft": 516.6666,
    "LocRight": -527.0833,
    "LocTop": -849.99994,
    "LocBottom": -1545.8333,
    "UIMapId": 1456,
    "Continent": "Kalimdor"
  },
  {
    "ID": 381,
    "MapID": 1,
    "AreaID": 1657,
    "AreaName": "Darnassus",
    "LocLeft": 2938.3628,
    "LocRight": 1880.0295,
    "LocTop": 10238.316,
    "LocBottom": 9532.587,
    "UIMapId": 1457,
    "Continent": "Kalimdor"
  },
  {
    "ID": 382,
    "MapID": 0,
    "AreaID": 1497,
    "AreaName": "Undercity",
    "LocLeft": 873.1926,
    "LocRight": -86.1824,
    "LocTop": 1877.9453,
    "LocBottom": 1237.8412,
    "UIMapId": 1458,
    "Continent": "Azeroth"
  },
  {
    "ID": 401,
    "MapID": 30,
    "AreaID": 2597,
    "AreaName": "AlteracValley",
    "LocLeft": 1781.2499,
    "LocRight": -2456.25,
    "LocTop": 1085.4166,
    "LocBottom": -1739.5833,
    "UIMapId": 1459,
    "Continent": "Azeroth"
  },
  {
    "ID": 443,
    "MapID": 489,
    "AreaID": 3277,
    "AreaName": "WarsongGulch",
    "LocLeft": 2041.6666,
    "LocRight": 895.8333,
    "LocTop": 1627.0833,
    "LocBottom": 862.49994,
    "UIMapId": 1460,
    "Continent": "Azeroth"
  },
  {
    "ID": 461,
    "MapID": 529,
    "AreaID": 3358,
    "AreaName": "ArathiBasin",
    "LocLeft": 1858.3333,
    "LocRight": 102.08333,
    "LocTop": 1508.3333,
    "LocBottom": 337.5,
    "UIMapId": 1461,
    "Continent": "Azeroth"
  },
  {
    "ID": 462,
    "MapID": 530,
    "AreaID": 3430,
    "AreaName": "EversongWoods",
    "LocLeft": -4487.5,
    "LocRight": -9412.5,
    "LocTop": 11041.666,
    "LocBottom": 7758.333,
    "UIMapId": 1941,
    "Continent": "Azeroth"
  },
  {
    "ID": 463,
    "MapID": 530,
    "AreaID": 3433,
    "AreaName": "Ghostlands",
    "LocLeft": -5283.333,
    "LocRight": -8583.333,
    "LocTop": 8266.666,
    "LocBottom": 6066.6665,
    "UIMapId": 1942,
    "Continent": "Azeroth"
  },
  {
    "ID": 464,
    "MapID": 530,
    "AreaID": 3524,
    "AreaName": "AzuremystIsle",
    "LocLeft": -10500.0,
    "LocRight": -14570.833,
    "LocTop": -2793.75,
    "LocBottom": -5508.333,
    "UIMapId": 1943,
    "Continent": "Kalimdor"
  },
  {
    "ID": 465,
    "MapID": 530,
    "AreaID": 3483,
    "AreaName": "Hellfire",
    "LocLeft": 5539.583,
    "LocRight": 375.0,
    "LocTop": 1481.25,
    "LocBottom": -1962.4999,
    "UIMapId": 1944,
    "Continent": "Expansion01"
  },
  {
    "ID": 466,
    "MapID": 530,
    "AreaID": 0,
    "AreaName": "Expansion01",
    "LocLeft": 12996.039,
    "LocRight": -4468.039,
    "LocTop": 5821.3594,
    "LocBottom": -5821.3594,
    "UIMapId": 0,
    "Continent": ""
  },
  {
    "ID": 467,
    "MapID": 530,
    "AreaID": 3521,
    "AreaName": "Zangarmarsh",
    "LocLeft": 9475.0,
    "LocRight": 4447.9165,
    "LocTop": 1935.4166,
    "LocBottom": -1416.6666,
    "UIMapId": 1946,
    "Continent": "Expansion01"
  },
  {
    "ID": 471,
    "MapID": 530,
    "AreaID": 3557,
    "AreaName": "TheExodar",
    "LocLeft": -11066.367,
    "LocRight": -12123.138,
    "LocTop": -3609.6833,
    "LocBottom": -4314.371,
    "UIMapId": 1947,
    "Continent": "Kalimdor"
  },
  {
    "ID": 473,
    "MapID": 530,
    "AreaID": 3520,
    "AreaName": "ShadowmoonValley",
    "LocLeft": 4225.0,
    "LocRight": -1275.0,
    "LocTop": -1947.9166,
    "LocBottom": -5614.583,
    "UIMapId": 1948,
    "Continent": "Expansion01"
  },
  {
    "ID": 475,
    "MapID": 530,
    "AreaID": 3522,
    "AreaName": "BladesEdgeMountains",
    "LocLeft": 8845.833,
    "LocRight": 3420.8333,
    "LocTop": 4408.333,
    "LocBottom": 791.6666,
    "UIMapId": 1949,
    "Continent": "Expansion01"
  },
  {
    "ID": 476,
    "MapID": 530,
    "AreaID": 3525,
    "AreaName": "BloodmystIsle",
    "LocLeft": -10075.0,
    "LocRight": -13337.499,
    "LocTop": -758.3333,
    "LocBottom": -2933.3333,
    "UIMapId": 1950,
    "Continent": "Kalimdor"
  },
  {
    "ID": 477,
    "MapID": 530,
    "AreaID": 3518,
    "AreaName": "Nagrand",
    "LocLeft": 10295.833,
    "LocRight": 4770.833,
    "LocTop": 41.666664,
    "LocBottom": -3641.6665,
    "UIMapId": 1951,
    "Continent": "Expansion01"
  },
  {
    "ID": 478,
    "MapID": 530,
    "AreaID": 3519,
    "AreaName": "TerokkarForest",
    "LocLeft": 7083.333,
    "LocRight": 1683.3333,
    "LocTop": -999.99994,
    "LocBottom": -4600.0,
    "UIMapId": 1952,
    "Continent": "Expansion01"
  },
  {
    "ID": 479,
    "MapID": 530,
    "AreaID": 3523,
    "AreaName": "Netherstorm",
    "LocLeft": 5483.333,
    "LocRight": -91.666664,
    "LocTop": 5456.25,
    "LocBottom": 1739.5833,
    "UIMapId": 1953,
    "Continent": "Expansion01"
  },
  {
    "ID": 480,
    "MapID": 530,
    "AreaID": 3487,
    "AreaName": "SilvermoonCity",
    "LocLeft": -6400.75,
    "LocRight": -7612.2085,
    "LocTop": 10153.709,
    "LocBottom": 9346.938,
    "UIMapId": 1954,
    "Continent": "Azeroth"
  },
  {
    "ID": 481,
    "MapID": 530,
    "AreaID": 3703,
    "AreaName": "ShattrathCity",
    "LocLeft": 6135.259,
    "LocRight": 4829.009,
    "LocTop": -1473.9545,
    "LocBottom": -2344.7878,
    "UIMapId": 1955,
    "Continent": "Expansion01"
  },
  {
    "ID": 482,
    "MapID": 566,
    "AreaID": 3820,
    "AreaName": "NetherstormArena",
    "LocLeft": 2660.4165,
    "LocRight": 389.5833,
    "LocTop": 2918.75,
    "LocBottom": 1404.1666,
    "UIMapId": 1953,
    "Continent": "Expansion01"
  },
  {
    "ID": 499,
    "MapID": 530,
    "AreaID": 4080,
    "AreaName": "Sunwell",
    "LocLeft": -5302.083,
    "LocRight": -8629.166,
    "LocTop": 13568.749,
    "LocBottom": 11350.0,
    "UIMapId": 0,
    "Continent": ""
  }
]