{
  "ClassName": "Shaman",
  "Loot": true,
  "PathFilename": "_pack\\1-20\\Draenei\\1-5_Azuremyst Isle.json",
  "PathThereAndBack": true,
  "PathReduceSteps": true,
  "Pull": {
    "Sequence": [
      {
        "Name": "Lightning Bolt",
        "Key": "2",
        "StopBeforeCast": true,
        "HasCastBar": true,
        "MinMana": 15
      }
    ]
  },
  "Combat": {
    "Sequence": [
      {
        "Name": "Lightning Bolt",
        "Key": "2",
        "StopBeforeCast": true,
        "HasCastBar": true,
        "MinMana": 15,
        "Requirement": "not InMeleeRange"
      },
      {
        "Name": "Healing Wave",
        "Key": "3",
        "Requirement": "Health%<40",
        "Cooldown": 10,
        "HasCastBar": true,
        "MinMana": 25
      },
      {
        "Name": "Approach",
        "Requirement": "not InMeleeRange",
        "Cooldown": 1
      },
      {
        "Name": "AutoAttack",
        "Requirement": "not AutoAttacking"
      }
    ]
  },
  "Parallel": {
    "Sequence": [
      {
        "Name": "Food",
        "StopBeforeCast": true,
        "AfterCastWaitBuff": true,
        "Key": "=",
        "Requirement": "Health%<30",
        "Cooldown": 10
      },
      {
        "Name": "Water",
        "StopBeforeCast": true,
        "AfterCastWaitBuff": true,
        "Key": "-",
        "Requirement": "Mana%<30",
        "Cooldown": 10
      }
    ]
  }
}
